__init__.py
py_arg/__init__.py
py_arg/aba_classes/__init__.py
py_arg/aba_classes/aba_framework.py
py_arg/aba_classes/instantiated_argument.py
py_arg/aba_classes/rule.py
py_arg/aba_classes/semantics/__init__.py
py_arg/aba_classes/semantics/get_admissible_extensions.py
py_arg/aba_classes/semantics/get_complete_extensions.py
py_arg/aba_classes/semantics/get_conflict_free_extensions.py
py_arg/aba_classes/semantics/get_grounded_extensions.py
py_arg/aba_classes/semantics/get_naive_extensions.py
py_arg/aba_classes/semantics/get_preferred_extensions.py
py_arg/aba_classes/semantics/get_semi_stable_extensions.py
py_arg/aba_classes/semantics/get_stable_extensions.py
py_arg/abstract_argumentation_classes/__init__.py
py_arg/abstract_argumentation_classes/abstract_argumentation_framework.py
py_arg/abstract_argumentation_classes/argument.py
py_arg/abstract_argumentation_classes/defeat.py
py_arg/algorithms/__init__.py
py_arg/algorithms/canonical_constructions/__init__.py
py_arg/algorithms/canonical_constructions/aux_operators.py
py_arg/algorithms/canonical_constructions/check_com_closed.py
py_arg/algorithms/canonical_constructions/check_conf_sens.py
py_arg/algorithms/canonical_constructions/check_contains_empty.py
py_arg/algorithms/canonical_constructions/check_dcl_tight.py
py_arg/algorithms/canonical_constructions/check_downward_closed.py
py_arg/algorithms/canonical_constructions/check_incomparable.py
py_arg/algorithms/canonical_constructions/check_intersection_in.py
py_arg/algorithms/canonical_constructions/check_non_empty.py
py_arg/algorithms/canonical_constructions/check_set_com_closed.py
py_arg/algorithms/canonical_constructions/check_set_conf_sens.py
py_arg/algorithms/canonical_constructions/check_tight.py
py_arg/algorithms/canonical_constructions/check_unary.py
py_arg/algorithms/canonical_constructions/check_union_closed.py
py_arg/algorithms/canonical_constructions/canonical_abaf/__init__.py
py_arg/algorithms/canonical_constructions/canonical_abaf/canonical_adm.py
python_argumentation-2.0.2.dist-info/LICENSE
python_argumentation-2.0.2.dist-info/METADATA
python_argumentation-2.0.2.dist-info/WHEEL
python_argumentation-2.0.2.dist-info/top_level.txt
python_argumentation-2.0.2.dist-info/RECORD
